{
  "node": {
    "7f0d00c839e01e5a22b55a194f415ab60d8f1d8f54": {
      "workers": {
        "app/page": {
          "moduleId": "(rsc)/./node_modules/next/dist/build/webpack/loaders/next-flight-action-entry-loader.js?actions=%5B%5B%22%2FUsers%2Fspr%2Ffertivisiion%20codelm%2Fnode_modules%2F%40clerk%2Fnextjs%2Fdist%2Fesm%2Fapp-router%2Fkeyless-actions.js%22%2C%5B%7B%22id%22%3A%227f0d00c839e01e5a22b55a194f415ab60d8f1d8f54%22%2C%22exportedName%22%3A%22deleteKeylessAction%22%7D%2C%7B%22id%22%3A%227f8eb88e743c3c6c81e61fbec558bdfde1d1ce6488%22%2C%22exportedName%22%3A%22createOrReadKeylessAction%22%7D%2C%7B%22id%22%3A%227fc581675bccd5e788034dfe2678abe2febd0a1feb%22%2C%22exportedName%22%3A%22syncKeylessConfigAction%22%7D%5D%5D%5D&__client_imported__=!",
          "async": false
        },
        "app/pricing/page": {
          "moduleId": "(rsc)/./node_modules/next/dist/build/webpack/loaders/next-flight-action-entry-loader.js?actions=%5B%5B%22%2FUsers%2Fspr%2Ffertivisiion%20codelm%2Fnode_modules%2F%40clerk%2Fnextjs%2Fdist%2Fesm%2Fapp-router%2Fkeyless-actions.js%22%2C%5B%7B%22id%22%3A%227f0d00c839e01e5a22b55a194f415ab60d8f1d8f54%22%2C%22exportedName%22%3A%22deleteKeylessAction%22%7D%2C%7B%22id%22%3A%227f8eb88e743c3c6c81e61fbec558bdfde1d1ce6488%22%2C%22exportedName%22%3A%22createOrReadKeylessAction%22%7D%2C%7B%22id%22%3A%227fc581675bccd5e788034dfe2678abe2febd0a1feb%22%2C%22exportedName%22%3A%22syncKeylessConfigAction%22%7D%5D%5D%5D&__client_imported__=!",
          "async": false
        }
      },
      "layer": {
        "app/page": "rsc",
        "app/pricing/page": "rsc"
      }
    },
    "7f8eb88e743c3c6c81e61fbec558bdfde1d1ce6488": {
      "workers": {
        "app/page": {
          "moduleId": "(rsc)/./node_modules/next/dist/build/webpack/loaders/next-flight-action-entry-loader.js?actions=%5B%5B%22%2FUsers%2Fspr%2Ffertivisiion%20codelm%2Fnode_modules%2F%40clerk%2Fnextjs%2Fdist%2Fesm%2Fapp-router%2Fkeyless-actions.js%22%2C%5B%7B%22id%22%3A%227f0d00c839e01e5a22b55a194f415ab60d8f1d8f54%22%2C%22exportedName%22%3A%22deleteKeylessAction%22%7D%2C%7B%22id%22%3A%227f8eb88e743c3c6c81e61fbec558bdfde1d1ce6488%22%2C%22exportedName%22%3A%22createOrReadKeylessAction%22%7D%2C%7B%22id%22%3A%227fc581675bccd5e788034dfe2678abe2febd0a1feb%22%2C%22exportedName%22%3A%22syncKeylessConfigAction%22%7D%5D%5D%5D&__client_imported__=!",
          "async": false
        },
        "app/pricing/page": {
          "moduleId": "(rsc)/./node_modules/next/dist/build/webpack/loaders/next-flight-action-entry-loader.js?actions=%5B%5B%22%2FUsers%2Fspr%2Ffertivisiion%20codelm%2Fnode_modules%2F%40clerk%2Fnextjs%2Fdist%2Fesm%2Fapp-router%2Fkeyless-actions.js%22%2C%5B%7B%22id%22%3A%227f0d00c839e01e5a22b55a194f415ab60d8f1d8f54%22%2C%22exportedName%22%3A%22deleteKeylessAction%22%7D%2C%7B%22id%22%3A%227f8eb88e743c3c6c81e61fbec558bdfde1d1ce6488%22%2C%22exportedName%22%3A%22createOrReadKeylessAction%22%7D%2C%7B%22id%22%3A%227fc581675bccd5e788034dfe2678abe2febd0a1feb%22%2C%22exportedName%22%3A%22syncKeylessConfigAction%22%7D%5D%5D%5D&__client_imported__=!",
          "async": false
        }
      },
      "layer": {
        "app/page": "rsc",
        "app/pricing/page": "rsc"
      }
    },
    "7fc581675bccd5e788034dfe2678abe2febd0a1feb": {
      "workers": {
        "app/page": {
          "moduleId": "(rsc)/./node_modules/next/dist/build/webpack/loaders/next-flight-action-entry-loader.js?actions=%5B%5B%22%2FUsers%2Fspr%2Ffertivisiion%20codelm%2Fnode_modules%2F%40clerk%2Fnextjs%2Fdist%2Fesm%2Fapp-router%2Fkeyless-actions.js%22%2C%5B%7B%22id%22%3A%227f0d00c839e01e5a22b55a194f415ab60d8f1d8f54%22%2C%22exportedName%22%3A%22deleteKeylessAction%22%7D%2C%7B%22id%22%3A%227f8eb88e743c3c6c81e61fbec558bdfde1d1ce6488%22%2C%22exportedName%22%3A%22createOrReadKeylessAction%22%7D%2C%7B%22id%22%3A%227fc581675bccd5e788034dfe2678abe2febd0a1feb%22%2C%22exportedName%22%3A%22syncKeylessConfigAction%22%7D%5D%5D%5D&__client_imported__=!",
          "async": false
        },
        "app/pricing/page": {
          "moduleId": "(rsc)/./node_modules/next/dist/build/webpack/loaders/next-flight-action-entry-loader.js?actions=%5B%5B%22%2FUsers%2Fspr%2Ffertivisiion%20codelm%2Fnode_modules%2F%40clerk%2Fnextjs%2Fdist%2Fesm%2Fapp-router%2Fkeyless-actions.js%22%2C%5B%7B%22id%22%3A%227f0d00c839e01e5a22b55a194f415ab60d8f1d8f54%22%2C%22exportedName%22%3A%22deleteKeylessAction%22%7D%2C%7B%22id%22%3A%227f8eb88e743c3c6c81e61fbec558bdfde1d1ce6488%22%2C%22exportedName%22%3A%22createOrReadKeylessAction%22%7D%2C%7B%22id%22%3A%227fc581675bccd5e788034dfe2678abe2febd0a1feb%22%2C%22exportedName%22%3A%22syncKeylessConfigAction%22%7D%5D%5D%5D&__client_imported__=!",
          "async": false
        }
      },
      "layer": {
        "app/page": "rsc",
        "app/pricing/page": "rsc"
      }
    },
    "7fd74b5dc5379a550d566635b20df6831e60b98320": {
      "workers": {
        "app/page": {
          "moduleId": "(action-browser)/./node_modules/next/dist/build/webpack/loaders/next-flight-action-entry-loader.js?actions=%5B%5B%22%2FUsers%2Fspr%2Ffertivisiion%20codelm%2Fnode_modules%2F%40clerk%2Fnextjs%2Fdist%2Fesm%2Fapp-router%2Fserver-actions.js%22%2C%5B%7B%22id%22%3A%227fd74b5dc5379a550d566635b20df6831e60b98320%22%2C%22exportedName%22%3A%22invalidateCacheAction%22%7D%5D%5D%5D&__client_imported__=true!",
          "async": false
        },
        "app/pricing/page": {
          "moduleId": "(action-browser)/./node_modules/next/dist/build/webpack/loaders/next-flight-action-entry-loader.js?actions=%5B%5B%22%2FUsers%2Fspr%2Ffertivisiion%20codelm%2Fnode_modules%2F%40clerk%2Fnextjs%2Fdist%2Fesm%2Fapp-router%2Fserver-actions.js%22%2C%5B%7B%22id%22%3A%227fd74b5dc5379a550d566635b20df6831e60b98320%22%2C%22exportedName%22%3A%22invalidateCacheAction%22%7D%5D%5D%5D&__client_imported__=true!",
          "async": false
        }
      },
      "layer": {
        "app/page": "action-browser",
        "app/pricing/page": "action-browser"
      }
    }
  },
  "edge": {},
  "encryptionKey": "Ciivc+M4K+ocUAvD3IMWUoNw6Bomna9l/hXBeL5RuEM="
}